ddsapi/__init__.py
ddsapi/api.py
ddsapi-0.6b1.dist-info/LICENSE
ddsapi-0.6b1.dist-info/METADATA
ddsapi-0.6b1.dist-info/WHEEL
ddsapi-0.6b1.dist-info/top_level.txt
ddsapi-0.6b1.dist-info/RECORD
