Metadata-Version: 2.1
Name: ddsapi
Version: 0.6b1
Summary: Python Client to access and download data from CMCC Data Delivery System (DDS)
Home-page: https://github.com/CMCC-Foundation/ddsapi-client/
Author: CMCC Data Delivery System Team
Author-email: dds-support@cmcc.it
License: Apache License, Version 2.0
Classifier: Development Status :: 4 - Beta
Classifier: Environment :: Web Environment
Classifier: Intended Audience :: Science/Research
Classifier: License :: OSI Approved :: Apache Software License
Classifier: Natural Language :: English
Classifier: Operating System :: OS Independent
Classifier: Programming Language :: Python :: 3
Classifier: Topic :: Scientific/Engineering :: Atmospheric Science
Classifier: Topic :: Scientific/Engineering :: Hydrology
Requires-Python: >=3.7
License-File: LICENSE
Requires-Dist: netCDF4 (>=1.5.3)
Requires-Dist: scipy (>=1.5.2)
Requires-Dist: requests (>=2.23.0)
Requires-Dist: xarray (==0.16.0)
